<?xml version="1.0" encoding="utf-8"?>
<!DOCTYPE hibernate-mapping PUBLIC "-//Hibernate/Hibernate Mapping DTD 3.0//EN"
"http://hibernate.sourceforge.net/hibernate-mapping-3.0.dtd">
<!-- 
    Mapping file autogenerated by MyEclipse Persistence Tools
-->
<hibernate-mapping>
    <class name="com.changpeng.models.Coursetype" table="coursetype">
        <id name="typeid" type="int">
            <column name="typeid" />
            <generator class="increment" />
        </id>
        <property name="typename" type="java.lang.String">
            <column name="typename" length="100" not-null="true" />
        </property>
        <property name="createuser" type="java.lang.String">
            <column name="createuser" length="45" />
        </property>
        <property name="createtime" type="java.util.Date">
            <column name="createtime" length="19" />
        </property>
        <property name="warecount" type="int">
            <column name="warecount" />
        </property>
        <set name="coursewares" inverse="true">
            <key>
                <column name="typeid" not-null="true" />
            </key>
            <one-to-many class="com.changpeng.models.Courseware" />
        </set>
    </class>
</hibernate-mapping>
