<?xml version="1.0" encoding="utf-8"?>
<!DOCTYPE hibernate-mapping PUBLIC "-//Hibernate/Hibernate Mapping DTD 3.0//EN"
"http://hibernate.sourceforge.net/hibernate-mapping-3.0.dtd">
<!-- 
    Mapping file autogenerated by MyEclipse Persistence Tools
-->
<hibernate-mapping>
    <class name="com.changpeng.models.LogClientRequest" table="log_client_request" catalog="saaspxxt">
        <id name="id" type="int">
            <column name="id" />
            <generator class="identity" />
        </id>
        <property name="groupid" type="int">
            <column name="groupid" />
        </property>
        <property name="method" type="java.lang.String">
            <column name="method" length="20" />
        </property>
        <property name="reqtime" type="timestamp">
            <column name="reqtime" />
        </property>
           <property name="restime" type="timestamp">
            <column name="restime">
            </column>
        </property>
      
        <property name="reqcontent" type="java.lang.String">
            <column name="reqcontent" length="65536" />
        </property>
        
                <property name="cpuid" type="java.lang.String">
            <column name="cpuid" length="100" />
        </property>
        
        
        <property name="rescontent" type="java.lang.String">
            <column name="rescontent" length="65536" />
        </property>
    </class>
</hibernate-mapping>
